README.rst
setup.py
./agglo_tk/__init__.py
./agglo_tk/exceptions.py
./agglo_tk/_private/__init__.py
./agglo_tk/_private/selector_match_visitor.py
./agglo_tk/_private/tree_element.py
./agglo_tk/design_patterns/visitor.py
./agglo_tk/io/__init__.py
./agglo_tk/io/input_handler.py
./agglo_tk/io/io.py
./agglo_tk/io/io_connection.py
./agglo_tk/io/io_connection_logs.py
./agglo_tk/io/io_criteria.py
./agglo_tk/io/io_criteria_string.py
./agglo_tk/io/io_device.py
./agglo_tk/io/io_device_serial.py
./agglo_tk/io/io_device_ssh.py
./agglo_tk/io/io_device_tcp.py
./agglo_tk/io/io_dumper.py
./agglo_tk/io/io_dumper_txt.py
./agglo_tk/io/io_hub.py
./agglo_tk/io/io_logs.py
./agglo_tk/io/io_selector.py
./agglo_tk/io/scapy/__init__.py
./agglo_tk/io/scapy/io_connection.py
./agglo_tk/io/scapy/io_criteria.py
./agglo_tk/io/scapy/io_device.py
./agglo_tk/selector/__init__.py
./agglo_tk/selector/complex_selector.py
./agglo_tk/selector/criteria.py
./agglo_tk/selector/criteria_path.py
./agglo_tk/selector/criteria_re.py
./agglo_tk/selector/criteria_string.py
./agglo_tk/selector/selector.py
./agglo_tk/tree/__init__.py
./agglo_tk/tree/builder.py
./agglo_tk/tree/leaf.py
./agglo_tk/tree/node.py
./agglo_tk/tree/tree.py
./agglo_tk/tree/tree_bool.py
./agglo_tk/utils/__init__.py
./agglo_tk/utils/argument_parser.py
./agglo_tk/utils/base_types.py
./agglo_tk/utils/command_runner.py
./agglo_tk/utils/config.py
./agglo_tk/utils/dynamic_class.py
./agglo_tk/utils/event.py
./agglo_tk/utils/frame_buffer.py
./agglo_tk/utils/friend.py
./agglo_tk/utils/limited_access_mixin.py
./agglo_tk/utils/limited_access_proxy.py
./agglo_tk/utils/misc.py
./agglo_tk/utils/module_loader.py
./agglo_tk/utils/rewrite_function.py
./agglo_tk/utils/ro_referencer.py
./agglo_tk/utils/serializable.py
./agglo_tk/utils/ssh_runner.py
./agglo_tk/utils/struct.py
./agglo_tk/utils/time.py
./agglo_tk/utils/trace.py
./agglo_tk/utils/test/__init__.py
./agglo_tk/utils/test/add_report_plugin.py
./agglo_tk/utils/test/fixtures.py
agglo_tk.egg-info/PKG-INFO
agglo_tk.egg-info/SOURCES.txt
agglo_tk.egg-info/dependency_links.txt
agglo_tk.egg-info/requires.txt
agglo_tk.egg-info/top_level.txt