Metadata-Version: 2.1
Name: agglo-tk
Version: 1.2.7
Summary: Library of various utils: io management, data selector, design patterns...
Home-page: http://sourceforge.net/projects/agglo/
Author: toubab
Author-email: eti.laurent@gmail.com
License: GPL/Proprietary
Platform: UNKNOWN
Classifier: Programming Language :: Python
Classifier: Development Status :: 3 - Alpha
Classifier: Natural Language :: English
Classifier: Operating System :: OS Independent
Classifier: Programming Language :: Python :: 3.6
Classifier: Topic :: Software Development
